odoo9_addon_account_payment_transfer_reconcile_batch-9.0.1.0.0-py2.7-nspkg.pth
odoo9_addon_account_payment_transfer_reconcile_batch-9.0.1.0.0.dist-info/top_level.txt
odoo9_addon_account_payment_transfer_reconcile_batch-9.0.1.0.0.dist-info/WHEEL
odoo9_addon_account_payment_transfer_reconcile_batch-9.0.1.0.0.dist-info/RECORD
odoo9_addon_account_payment_transfer_reconcile_batch-9.0.1.0.0.dist-info/metadata.json
odoo9_addon_account_payment_transfer_reconcile_batch-9.0.1.0.0.dist-info/DESCRIPTION.rst
odoo9_addon_account_payment_transfer_reconcile_batch-9.0.1.0.0.dist-info/METADATA
odoo9_addon_account_payment_transfer_reconcile_batch-9.0.1.0.0.dist-info/namespace_packages.txt
odoo_addons/account_payment_transfer_reconcile_batch/__openerp__.py
odoo_addons/account_payment_transfer_reconcile_batch/__init__.py
odoo_addons/account_payment_transfer_reconcile_batch/README.rst
odoo_addons/account_payment_transfer_reconcile_batch/models/__init__.py
odoo_addons/account_payment_transfer_reconcile_batch/models/bank_payment_line.py
odoo_addons/account_payment_transfer_reconcile_batch/i18n/it.po
odoo_addons/account_payment_transfer_reconcile_batch/i18n/es.po
odoo_addons/account_payment_transfer_reconcile_batch/i18n/sl.po
odoo_addons/account_payment_transfer_reconcile_batch/i18n/nl.po
odoo_addons/account_payment_transfer_reconcile_batch/i18n/de.po
odoo_addons/account_payment_transfer_reconcile_batch/i18n/fr.po
odoo_addons/account_payment_transfer_reconcile_batch/i18n/pt_BR.po
odoo_addons/account_payment_transfer_reconcile_batch/wizard/account_payment_line_create.py
odoo_addons/account_payment_transfer_reconcile_batch/wizard/__init__.py
odoo_addons/account_payment_transfer_reconcile_batch/tests/test_account_payment_transfer_reconcile_batch.py
odoo_addons/account_payment_transfer_reconcile_batch/tests/__init__.py
